[
  {
    "id": "game-2026-06-13-vs-raptors",
    "slug": "game-2026-06-13-vs-raptors",
    "source": "game-record",
    "autoGenerated": true,
    "category": "경기 기록",
    "title": "다윗 야구 선교단, Team Raptors전 경기 기록 업데이트",
    "date": "2026-06-13",
    "summary": "다윗 야구 선교단은 10안타 0홈런 6도루를 기록했습니다. 주요 기록: 3루타 안창혁(3회) 김해찬(4회) 이용재(4회), 2루타 김재영(2회) 은영환(4회) 권태헌(2회).",
    "content": "<p>다윗 야구 선교단은 Team Raptors전에서 10안타 0홈런 6도루를 기록했습니다.</p><p>주요 기록은 3루타 안창혁(3회) 김해찬(4회) 이용재(4회), 2루타 김재영(2회) 은영환(4회) 권태헌(2회)입니다.</p><p><a href=\"/games/2026-06-13-vs-raptors\">경기 상세 기록 보기</a></p>",
    "link": "/games/2026-06-13-vs-raptors",
    "gameId": "2026-06-13-vs-raptors",
    "youtube": null
  },
  {
    "id": "game-2026-06-06-vs-lx",
    "slug": "game-2026-06-06-vs-lx",
    "source": "game-record",
    "autoGenerated": true,
    "category": "경기 기록",
    "title": "다윗 야구 선교단, LX 일스야구단전 경기 기록 업데이트",
    "date": "2026-06-06",
    "summary": "다윗 야구 선교단은 7안타 0홈런 5도루를 기록했습니다. 주요 기록: 2루타 최지민(3회), 도루 최지민(3회,5회) 장재형(1회,3회) 이영원(1회,5회) 박양원(4회) 김영지(3회) 박의현(3회,5회) 선예환(5회) 김명선(2회) 지성찬(2회).",
    "content": "<p>다윗 야구 선교단은 LX 일스야구단전에서 7안타 0홈런 5도루를 기록했습니다.</p><p>주요 기록은 2루타 최지민(3회), 도루 최지민(3회,5회) 장재형(1회,3회) 이영원(1회,5회) 박양원(4회) 김영지(3회) 박의현(3회,5회) 선예환(5회) 김명선(2회) 지성찬(2회)입니다.</p><p><a href=\"/games/2026-06-06-vs-lx\">경기 상세 기록 보기</a></p>",
    "link": "/games/2026-06-06-vs-lx",
    "gameId": "2026-06-06-vs-lx",
    "youtube": {
      "videoCode": "JXliKeGGe14",
      "title": "26.06.06 D조 vs LX 일스야구단",
      "publishedAt": "2026-06-06",
      "youtubeUrl": "https://www.youtube.com/watch?v=JXliKeGGe14",
      "thumbnail": "https://i.ytimg.com/vi/JXliKeGGe14/hq720.jpg"
    }
  },
  {
    "id": "game-2026-05-30-vs-11st",
    "slug": "game-2026-05-30-vs-11st",
    "source": "game-record",
    "autoGenerated": true,
    "category": "경기 기록",
    "title": "다윗 야구 선교단, 11번가 와이번스전 경기 기록 업데이트",
    "date": "2026-05-30",
    "summary": "다윗 야구 선교단은 7안타 1홈런 2도루를 기록했습니다. 주요 기록: 홈런 은영환(4회), 3루타 은영환(2회).",
    "content": "<p>다윗 야구 선교단은 11번가 와이번스전에서 7안타 1홈런 2도루를 기록했습니다.</p><p>주요 기록은 홈런 은영환(4회), 3루타 은영환(2회)입니다.</p><p><a href=\"/games/2026-05-30-vs-11st\">경기 상세 기록 보기</a></p>",
    "link": "/games/2026-05-30-vs-11st",
    "gameId": "2026-05-30-vs-11st",
    "youtube": {
      "videoCode": "v9PPNTJB5lE",
      "title": "26.05.30 D조 vs 11번가 와이번스",
      "publishedAt": "2026-05-30",
      "youtubeUrl": "https://www.youtube.com/watch?v=v9PPNTJB5lE",
      "thumbnail": "https://i.ytimg.com/vi/v9PPNTJB5lE/hq720.jpg"
    }
  },
  {
    "id": "game-2026-05-23-vs-koreauniv",
    "slug": "game-2026-05-23-vs-koreauniv",
    "source": "game-record",
    "autoGenerated": true,
    "category": "경기 기록",
    "title": "다윗 야구 선교단, 고려대학교 데몽전 경기 기록 업데이트",
    "date": "2026-05-23",
    "summary": "다윗 야구 선교단은 11안타 1홈런 3도루를 기록했습니다. 주요 기록: 홈런 선예환(5회), 3루타 은영환(2회) 윤진석(2회).",
    "content": "<p>다윗 야구 선교단은 고려대학교 데몽전에서 11안타 1홈런 3도루를 기록했습니다.</p><p>주요 기록은 홈런 선예환(5회), 3루타 은영환(2회) 윤진석(2회)입니다.</p><p><a href=\"/games/2026-05-23-vs-koreauniv\">경기 상세 기록 보기</a></p>",
    "link": "/games/2026-05-23-vs-koreauniv",
    "gameId": "2026-05-23-vs-koreauniv",
    "youtube": {
      "videoCode": "jWTJ8OXmQig",
      "title": "26.05.23 D조 vs 서강가브리엘스",
      "publishedAt": "2026-05-23",
      "youtubeUrl": "https://www.youtube.com/watch?v=jWTJ8OXmQig",
      "thumbnail": "https://i.ytimg.com/vi/jWTJ8OXmQig/hq720.jpg"
    }
  },
  {
    "id": "game-2026-05-09-vs-anjin",
    "slug": "game-2026-05-09-vs-anjin",
    "source": "game-record",
    "autoGenerated": true,
    "category": "경기 기록",
    "title": "다윗 야구 선교단, 안진회계법인전 경기 기록 업데이트",
    "date": "2026-05-09",
    "summary": "다윗 야구 선교단은 8안타 0홈런 9도루를 기록했습니다. 주요 기록: 3루타 김재영(1회,5회), 2루타 지성찬(1회).",
    "content": "<p>다윗 야구 선교단은 안진회계법인전에서 8안타 0홈런 9도루를 기록했습니다.</p><p>주요 기록은 3루타 김재영(1회,5회), 2루타 지성찬(1회)입니다.</p><p><a href=\"/games/2026-05-09-vs-anjin\">경기 상세 기록 보기</a></p>",
    "link": "/games/2026-05-09-vs-anjin",
    "gameId": "2026-05-09-vs-anjin",
    "youtube": null
  },
  {
    "id": "game-2026-05-02-vs-mavericks",
    "slug": "game-2026-05-02-vs-mavericks",
    "source": "game-record",
    "autoGenerated": true,
    "category": "경기 기록",
    "title": "다윗 야구 선교단, Mavericks전 경기 기록 업데이트",
    "date": "2026-05-02",
    "summary": "다윗 야구 선교단은 11안타 0홈런 17도루를 기록했습니다. 주요 기록: 3루타 이홍일(3회), 2루타 박의현(3회) 은영환(4회).",
    "content": "<p>다윗 야구 선교단은 Mavericks전에서 11안타 0홈런 17도루를 기록했습니다.</p><p>주요 기록은 3루타 이홍일(3회), 2루타 박의현(3회) 은영환(4회)입니다.</p><p><a href=\"/games/2026-05-02-vs-mavericks\">경기 상세 기록 보기</a></p>",
    "link": "/games/2026-05-02-vs-mavericks",
    "gameId": "2026-05-02-vs-mavericks",
    "youtube": {
      "videoCode": "uaVwOn0_kXA",
      "title": "26.05.02 D조 vs Mavericks",
      "publishedAt": "2026-05-02",
      "youtubeUrl": "https://www.youtube.com/watch?v=uaVwOn0_kXA",
      "thumbnail": "https://i.ytimg.com/vi/uaVwOn0_kXA/hq720.jpg"
    }
  },
  {
    "id": "game-2026-04-18-vs-bluehoodies",
    "slug": "game-2026-04-18-vs-bluehoodies",
    "source": "game-record",
    "autoGenerated": true,
    "category": "경기 기록",
    "title": "다윗 야구 선교단, (유신)블루후디스전 경기 기록 업데이트",
    "date": "2026-04-18",
    "summary": "다윗 야구 선교단은 10안타 1홈런 5도루를 기록했습니다. 주요 기록: 홈런 박의현(4회), 3루타 반석훈(3회,4회).",
    "content": "<p>다윗 야구 선교단은 (유신)블루후디스전에서 10안타 1홈런 5도루를 기록했습니다.</p><p>주요 기록은 홈런 박의현(4회), 3루타 반석훈(3회,4회)입니다.</p><p><a href=\"/games/2026-04-18-vs-bluehoodies\">경기 상세 기록 보기</a></p>",
    "link": "/games/2026-04-18-vs-bluehoodies",
    "gameId": "2026-04-18-vs-bluehoodies",
    "youtube": null
  },
  {
    "id": "game-2026-04-18-vs-sungnamob",
    "slug": "game-2026-04-18-vs-sungnamob",
    "source": "game-record",
    "autoGenerated": true,
    "category": "경기 기록",
    "title": "다윗 야구 선교단, 성남OB전 경기 기록 업데이트",
    "date": "2026-04-18",
    "summary": "다윗 야구 선교단은 9안타 1홈런 11도루를 기록했습니다. 주요 기록: 홈런 권태헌(3회), 3루타 반석훈(1회).",
    "content": "<p>다윗 야구 선교단은 성남OB전에서 9안타 1홈런 11도루를 기록했습니다.</p><p>주요 기록은 홈런 권태헌(3회), 3루타 반석훈(1회)입니다.</p><p><a href=\"/games/2026-04-18-vs-sungnamob\">경기 상세 기록 보기</a></p>",
    "link": "/games/2026-04-18-vs-sungnamob",
    "gameId": "2026-04-18-vs-sungnamob",
    "youtube": {
      "videoCode": "YOEK-uy5Mz4",
      "title": "26.04.18 A조 vs 성남OB",
      "publishedAt": "2026-04-18",
      "youtubeUrl": "https://www.youtube.com/watch?v=YOEK-uy5Mz4",
      "thumbnail": "https://i.ytimg.com/vi/YOEK-uy5Mz4/hq720.jpg"
    }
  },
  {
    "id": "game-2026-04-11-vs-mavericks",
    "slug": "game-2026-04-11-vs-mavericks",
    "source": "game-record",
    "autoGenerated": true,
    "category": "경기 기록",
    "title": "다윗 야구 선교단, Mavericks전 경기 기록 업데이트",
    "date": "2026-04-11",
    "summary": "다윗 야구 선교단은 4안타 0홈런 7도루를 기록했습니다. 주요 기록: 2루타 정선호(3회) 김재영(1회), 도루 곽우섭(1회,2회,4회) 서상원(1회,4회) 신상윤(4회) 정선호(1회,3회) 지성찬(3회) 김희열(2회) 노혁진(2회) 선예환(2회).",
    "content": "<p>다윗 야구 선교단은 Mavericks전에서 4안타 0홈런 7도루를 기록했습니다.</p><p>주요 기록은 2루타 정선호(3회) 김재영(1회), 도루 곽우섭(1회,2회,4회) 서상원(1회,4회) 신상윤(4회) 정선호(1회,3회) 지성찬(3회) 김희열(2회) 노혁진(2회) 선예환(2회)입니다.</p><p><a href=\"/games/2026-04-11-vs-mavericks\">경기 상세 기록 보기</a></p>",
    "link": "/games/2026-04-11-vs-mavericks",
    "gameId": "2026-04-11-vs-mavericks",
    "youtube": {
      "videoCode": "KlNeh6USsR8",
      "title": "26.04.11 D조 vs Mavericks",
      "publishedAt": "2026-04-11",
      "youtubeUrl": "https://www.youtube.com/watch?v=KlNeh6USsR8",
      "thumbnail": "https://i.ytimg.com/vi/KlNeh6USsR8/hq720.jpg"
    }
  },
  {
    "id": "game-2026-04-11-vs-nom",
    "slug": "game-2026-04-11-vs-nom",
    "source": "game-record",
    "autoGenerated": true,
    "category": "경기 기록",
    "title": "다윗 야구 선교단, N.O.M (Need Our Moment)전 경기 기록 업데이트",
    "date": "2026-04-11",
    "summary": "다윗 야구 선교단은 10안타 0홈런 8도루를 기록했습니다. 주요 기록: 2루타 강태웅(1회,5회) 진승용(1회), 도루 반석훈(1회,2회) 선예환(2회) 진승용(4회) 박의현(3회) 성백동(3회).",
    "content": "<p>다윗 야구 선교단은 N.O.M (Need Our Moment)전에서 10안타 0홈런 8도루를 기록했습니다.</p><p>주요 기록은 2루타 강태웅(1회,5회) 진승용(1회), 도루 반석훈(1회,2회) 선예환(2회) 진승용(4회) 박의현(3회) 성백동(3회)입니다.</p><p><a href=\"/games/2026-04-11-vs-nom\">경기 상세 기록 보기</a></p>",
    "link": "/games/2026-04-11-vs-nom",
    "gameId": "2026-04-11-vs-nom",
    "youtube": {
      "videoCode": "iujwrHxdOgE",
      "title": "26.04.11 D조 vs 서강가브리엘스",
      "publishedAt": "2026-04-11",
      "youtubeUrl": "https://www.youtube.com/watch?v=iujwrHxdOgE",
      "thumbnail": "https://i.ytimg.com/vi/iujwrHxdOgE/hq720.jpg"
    }
  },
  {
    "id": "game-2026-03-28-vs-daslgis",
    "slug": "game-2026-03-28-vs-daslgis",
    "source": "game-record",
    "autoGenerated": true,
    "category": "경기 기록",
    "title": "다윗 야구 선교단, 다슬기스OB전 경기 기록 업데이트",
    "date": "2026-03-28",
    "summary": "다윗 야구 선교단은 8안타 0홈런 5도루를 기록했습니다. 주요 기록: 3루타 은영환(3회), 2루타 이영빈(2회) 이원재(2회) 조상호(1회) 오세주(2회).",
    "content": "<p>다윗 야구 선교단은 다슬기스OB전에서 8안타 0홈런 5도루를 기록했습니다.</p><p>주요 기록은 3루타 은영환(3회), 2루타 이영빈(2회) 이원재(2회) 조상호(1회) 오세주(2회)입니다.</p><p><a href=\"/games/2026-03-28-vs-daslgis\">경기 상세 기록 보기</a></p>",
    "link": "/games/2026-03-28-vs-daslgis",
    "gameId": "2026-03-28-vs-daslgis",
    "youtube": {
      "videoCode": "MSCHCzSJfYs",
      "title": "26.03.28 A조 vs 다슬기스OB",
      "publishedAt": "2026-03-28",
      "youtubeUrl": "https://www.youtube.com/watch?v=MSCHCzSJfYs",
      "thumbnail": "https://i.ytimg.com/vi/MSCHCzSJfYs/hq720.jpg"
    }
  },
  {
    "id": "game-2026-03-14-vs-laeob",
    "slug": "game-2026-03-14-vs-laeob",
    "source": "game-record",
    "autoGenerated": true,
    "category": "경기 기록",
    "title": "다윗 야구 선교단, 동국대학교 LAE OB전 경기 기록 업데이트",
    "date": "2026-03-14",
    "summary": "다윗 야구 선교단은 9안타 0홈런 3도루를 기록했습니다. 주요 기록: 2루타 김재영(4회) 선예환(3회) 김명선(3회) 성백동(2회), 도루 선예환(4회) 성백동(3회) 이효재(4회) 최영규(1회) 이용성(4회) 윤재선(2회,4회).",
    "content": "<p>다윗 야구 선교단은 동국대학교 LAE OB전에서 9안타 0홈런 3도루를 기록했습니다.</p><p>주요 기록은 2루타 김재영(4회) 선예환(3회) 김명선(3회) 성백동(2회), 도루 선예환(4회) 성백동(3회) 이효재(4회) 최영규(1회) 이용성(4회) 윤재선(2회,4회)입니다.</p><p><a href=\"/games/2026-03-14-vs-laeob\">경기 상세 기록 보기</a></p>",
    "link": "/games/2026-03-14-vs-laeob",
    "gameId": "2026-03-14-vs-laeob",
    "youtube": {
      "videoCode": "9hXt1I94Ves",
      "title": "26.03.14 A조 vs 동국대학교 LAE OB",
      "publishedAt": "2026-03-14",
      "youtubeUrl": "https://www.youtube.com/watch?v=9hXt1I94Ves",
      "thumbnail": "https://i.ytimg.com/vi/9hXt1I94Ves/hq720.jpg"
    }
  },
  {
    "id": "game-2026-02-28-vs-stone",
    "slug": "game-2026-02-28-vs-stone",
    "source": "game-record",
    "autoGenerated": true,
    "category": "경기 기록",
    "title": "다윗 야구 선교단, 돌멩이야구단 D전 경기 기록 업데이트",
    "date": "2026-02-28",
    "summary": "다윗 야구 선교단은 6안타 0홈런 5도루를 기록했습니다. 주요 기록: 3루타 이용관(3회) 박세찬(4회), 2루타 전광(3회) 홍태화(4회) 오치송(3회).",
    "content": "<p>다윗 야구 선교단은 돌멩이야구단 D전에서 6안타 0홈런 5도루를 기록했습니다.</p><p>주요 기록은 3루타 이용관(3회) 박세찬(4회), 2루타 전광(3회) 홍태화(4회) 오치송(3회)입니다.</p><p><a href=\"/games/2026-02-28-vs-stone\">경기 상세 기록 보기</a></p>",
    "link": "/games/2026-02-28-vs-stone",
    "gameId": "2026-02-28-vs-stone",
    "youtube": {
      "videoCode": "cib8TRpE1J0",
      "title": "26.02.28 D조 vs 돌멩이야구단 D",
      "publishedAt": "2026-02-28",
      "youtubeUrl": "https://www.youtube.com/watch?v=cib8TRpE1J0",
      "thumbnail": "https://i.ytimg.com/vi/cib8TRpE1J0/hq720.jpg"
    }
  },
  {
    "id": "game-2026-02-21-vs-nom",
    "slug": "game-2026-02-21-vs-nom",
    "source": "game-record",
    "autoGenerated": true,
    "category": "경기 기록",
    "title": "다윗 야구 선교단, N.O.M (Need Our Moment)전 경기 기록 업데이트",
    "date": "2026-02-21",
    "summary": "다윗 야구 선교단은 17안타 2홈런 4도루를 기록했습니다. 주요 기록: 홈런 선예환(4회) 박의현(2회), 3루타 최정훈(2회).",
    "content": "<p>다윗 야구 선교단은 N.O.M (Need Our Moment)전에서 17안타 2홈런 4도루를 기록했습니다.</p><p>주요 기록은 홈런 선예환(4회) 박의현(2회), 3루타 최정훈(2회)입니다.</p><p><a href=\"/games/2026-02-21-vs-nom\">경기 상세 기록 보기</a></p>",
    "link": "/games/2026-02-21-vs-nom",
    "gameId": "2026-02-21-vs-nom",
    "youtube": {
      "videoCode": "WmThvON9E3Y",
      "title": "26.02.21 A조 vs N.O.M (Need Our Moment)",
      "publishedAt": "2026-02-21",
      "youtubeUrl": "https://www.youtube.com/watch?v=WmThvON9E3Y",
      "thumbnail": "https://i.ytimg.com/vi/WmThvON9E3Y/hq720.jpg"
    }
  },
  {
    "id": "game-2026-01-31-vs-sogang",
    "slug": "game-2026-01-31-vs-sogang",
    "source": "game-record",
    "autoGenerated": true,
    "category": "경기 기록",
    "title": "다윗 야구 선교단, 서강가브리엘스전 경기 기록 업데이트",
    "date": "2026-01-31",
    "summary": "다윗 야구 선교단은 9안타 0홈런 7도루를 기록했습니다. 주요 기록: 3루타 오치송(1회) 은영환(1회), 2루타 이효재(2회) 은영환(2회) 김명선(1회).",
    "content": "<p>다윗 야구 선교단은 서강가브리엘스전에서 9안타 0홈런 7도루를 기록했습니다.</p><p>주요 기록은 3루타 오치송(1회) 은영환(1회), 2루타 이효재(2회) 은영환(2회) 김명선(1회)입니다.</p><p><a href=\"/games/2026-01-31-vs-sogang\">경기 상세 기록 보기</a></p>",
    "link": "/games/2026-01-31-vs-sogang",
    "gameId": "2026-01-31-vs-sogang",
    "youtube": null
  },
  {
    "id": "game-2026-01-10-vs-gymonsters",
    "slug": "game-2026-01-10-vs-gymonsters",
    "source": "game-record",
    "autoGenerated": true,
    "category": "경기 기록",
    "title": "다윗 야구 선교단, GY몬스터즈전 경기 기록 업데이트",
    "date": "2026-01-10",
    "summary": "다윗 야구 선교단은 2안타 0홈런 8도루를 기록했습니다. 주요 기록: 3루타 홍기성(2회) 박의현(3회), 2루타 백경민(1회) 강유성(3회,5회).",
    "content": "<p>다윗 야구 선교단은 GY몬스터즈전에서 2안타 0홈런 8도루를 기록했습니다.</p><p>주요 기록은 3루타 홍기성(2회) 박의현(3회), 2루타 백경민(1회) 강유성(3회,5회)입니다.</p><p><a href=\"/games/2026-01-10-vs-gymonsters\">경기 상세 기록 보기</a></p>",
    "link": "/games/2026-01-10-vs-gymonsters",
    "gameId": "2026-01-10-vs-gymonsters",
    "youtube": null
  },
  {
    "id": "game-2026-01-03-vs-cubs2",
    "slug": "game-2026-01-03-vs-cubs2",
    "source": "game-record",
    "autoGenerated": true,
    "category": "경기 기록",
    "title": "다윗 야구 선교단, 시카고컵스2전 경기 기록 업데이트",
    "date": "2026-01-03",
    "summary": "다윗 야구 선교단은 12안타 0홈런 14도루를 기록했습니다. 주요 기록: 2루타 성백동(3회) 김상현(1회) 서지용(1회), 도루 성백동(2회,3회) 김재영(1회,2회) 선예환(1회) 박의현(2회,3회) 오치송(2회,3회) 서우성(1회) 김명선(3회) 이준민(1회,4회) 백승훈(2회,4회) 김상현(5회) 반석훈(3회) 은영환(4회) 민승기(5회).",
    "content": "<p>다윗 야구 선교단은 시카고컵스2전에서 12안타 0홈런 14도루를 기록했습니다.</p><p>주요 기록은 2루타 성백동(3회) 김상현(1회) 서지용(1회), 도루 성백동(2회,3회) 김재영(1회,2회) 선예환(1회) 박의현(2회,3회) 오치송(2회,3회) 서우성(1회) 김명선(3회) 이준민(1회,4회) 백승훈(2회,4회) 김상현(5회) 반석훈(3회) 은영환(4회) 민승기(5회)입니다.</p><p><a href=\"/games/2026-01-03-vs-cubs2\">경기 상세 기록 보기</a></p>",
    "link": "/games/2026-01-03-vs-cubs2",
    "gameId": "2026-01-03-vs-cubs2",
    "youtube": null
  },
  {
    "id": "game-2025-12-20-vs-polaris",
    "slug": "game-2025-12-20-vs-polaris",
    "source": "game-record",
    "autoGenerated": true,
    "category": "경기 기록",
    "title": "다윗 야구 선교단, Polaris전 경기 기록 업데이트",
    "date": "2025-12-20",
    "summary": "다윗 야구 선교단은 13안타 1홈런 13도루를 기록했습니다. 주요 기록: 홈런 김명선(2회), 3루타 정대영(1회).",
    "content": "<p>다윗 야구 선교단은 Polaris전에서 13안타 1홈런 13도루를 기록했습니다.</p><p>주요 기록은 홈런 김명선(2회), 3루타 정대영(1회)입니다.</p><p><a href=\"/games/2025-12-20-vs-polaris\">경기 상세 기록 보기</a></p>",
    "link": "/games/2025-12-20-vs-polaris",
    "gameId": "2025-12-20-vs-polaris",
    "youtube": null
  },
  {
    "id": "game-2025-12-06-vs-gameblers",
    "slug": "game-2025-12-06-vs-gameblers",
    "source": "game-record",
    "autoGenerated": true,
    "category": "경기 기록",
    "title": "다윗 야구 선교단, 놀음꾼들(Gamebler's)전 경기 기록 업데이트",
    "date": "2025-12-06",
    "summary": "다윗 야구 선교단은 10안타 0홈런 8도루를 기록했습니다. 주요 기록: 2루타 박희준(4회) 김민수(4회) 박의현(4회) 전병진(4회) 선예환(4회) 김재영(3회) 지성찬(2회), 도루 안현욱(2회) 정준기(1회,3회) 박의현(1회) 반석훈(2회,4회) 은영환(1회) 성백동(1회) 김재영(4회).",
    "content": "<p>다윗 야구 선교단은 놀음꾼들(Gamebler's)전에서 10안타 0홈런 8도루를 기록했습니다.</p><p>주요 기록은 2루타 박희준(4회) 김민수(4회) 박의현(4회) 전병진(4회) 선예환(4회) 김재영(3회) 지성찬(2회), 도루 안현욱(2회) 정준기(1회,3회) 박의현(1회) 반석훈(2회,4회) 은영환(1회) 성백동(1회) 김재영(4회)입니다.</p><p><a href=\"/games/2025-12-06-vs-gameblers\">경기 상세 기록 보기</a></p>",
    "link": "/games/2025-12-06-vs-gameblers",
    "gameId": "2025-12-06-vs-gameblers",
    "youtube": null
  },
  {
    "id": "game-2025-12-06-vs-slayers",
    "slug": "game-2025-12-06-vs-slayers",
    "source": "game-record",
    "autoGenerated": true,
    "category": "경기 기록",
    "title": "다윗 야구 선교단, Slayers전 경기 기록 업데이트",
    "date": "2025-12-06",
    "summary": "다윗 야구 선교단은 7안타 0홈런 13도루를 기록했습니다. 주요 기록: 2루타 김재영(2회) 지성찬(3회) 성백동(3회), 도루 김재영(1회,4회) 박의현(1회) 선예환(1회,3회,4회) 조영중(2회) 은영환(2회) 오대열(3회) 서동현(3회) 김태훈(5회) 이창규(4회) 정보근(4회) 문건호(3회).",
    "content": "<p>다윗 야구 선교단은 Slayers전에서 7안타 0홈런 13도루를 기록했습니다.</p><p>주요 기록은 2루타 김재영(2회) 지성찬(3회) 성백동(3회), 도루 김재영(1회,4회) 박의현(1회) 선예환(1회,3회,4회) 조영중(2회) 은영환(2회) 오대열(3회) 서동현(3회) 김태훈(5회) 이창규(4회) 정보근(4회) 문건호(3회)입니다.</p><p><a href=\"/games/2025-12-06-vs-slayers\">경기 상세 기록 보기</a></p>",
    "link": "/games/2025-12-06-vs-slayers",
    "gameId": "2025-12-06-vs-slayers",
    "youtube": null
  },
  {
    "id": "game-2025-11-29-vs-11st",
    "slug": "game-2025-11-29-vs-11st",
    "source": "game-record",
    "autoGenerated": true,
    "category": "경기 기록",
    "title": "다윗 야구 선교단, 11번가 와이번스전 경기 기록 업데이트",
    "date": "2025-11-29",
    "summary": "다윗 야구 선교단은 10안타 0홈런 1도루를 기록했습니다. 주요 기록: 3루타 박의현(1회) 선예환(1회) 은영환(1회), 2루타 정의민(1회) 박의현(1회) 서우성(1회) 김명선(2회).",
    "content": "<p>다윗 야구 선교단은 11번가 와이번스전에서 10안타 0홈런 1도루를 기록했습니다.</p><p>주요 기록은 3루타 박의현(1회) 선예환(1회) 은영환(1회), 2루타 정의민(1회) 박의현(1회) 서우성(1회) 김명선(2회)입니다.</p><p><a href=\"/games/2025-11-29-vs-11st\">경기 상세 기록 보기</a></p>",
    "link": "/games/2025-11-29-vs-11st",
    "gameId": "2025-11-29-vs-11st",
    "youtube": null
  },
  {
    "id": "game-2025-11-22-vs-koreabank",
    "slug": "game-2025-11-22-vs-koreabank",
    "source": "game-record",
    "autoGenerated": true,
    "category": "경기 기록",
    "title": "다윗 야구 선교단, 한국은행 야구부전 경기 기록 업데이트",
    "date": "2025-11-22",
    "summary": "다윗 야구 선교단은 14안타 1홈런 2도루를 기록했습니다. 주요 기록: 홈런 박의현(4회), 3루타 반석훈(1회) 박의현(2회).",
    "content": "<p>다윗 야구 선교단은 한국은행 야구부전에서 14안타 1홈런 2도루를 기록했습니다.</p><p>주요 기록은 홈런 박의현(4회), 3루타 반석훈(1회) 박의현(2회)입니다.</p><p><a href=\"/games/2025-11-22-vs-koreabank\">경기 상세 기록 보기</a></p>",
    "link": "/games/2025-11-22-vs-koreabank",
    "gameId": "2025-11-22-vs-koreabank",
    "youtube": null
  },
  {
    "id": "game-2025-11-08-vs-mavericks",
    "slug": "game-2025-11-08-vs-mavericks",
    "source": "game-record",
    "autoGenerated": true,
    "category": "경기 기록",
    "title": "다윗 야구 선교단, Mavericks전 경기 기록 업데이트",
    "date": "2025-11-08",
    "summary": "다윗 야구 선교단은 5안타 0홈런 9도루를 기록했습니다. 주요 기록: 3루타 이홍일(3회) 박의현(1회), 2루타 정종윤(2회) 박의현(2회).",
    "content": "<p>다윗 야구 선교단은 Mavericks전에서 5안타 0홈런 9도루를 기록했습니다.</p><p>주요 기록은 3루타 이홍일(3회) 박의현(1회), 2루타 정종윤(2회) 박의현(2회)입니다.</p><p><a href=\"/games/2025-11-08-vs-mavericks\">경기 상세 기록 보기</a></p>",
    "link": "/games/2025-11-08-vs-mavericks",
    "gameId": "2025-11-08-vs-mavericks",
    "youtube": null
  },
  {
    "id": "game-2025-11-01-vs-ibk",
    "slug": "game-2025-11-01-vs-ibk",
    "source": "game-record",
    "autoGenerated": true,
    "category": "경기 기록",
    "title": "다윗 야구 선교단, ibk야구단전 경기 기록 업데이트",
    "date": "2025-11-01",
    "summary": "다윗 야구 선교단은 10안타 0홈런 4도루를 기록했습니다. 주요 기록: 3루타 강대철(3회) 박의현(2회) 은영환(2회), 2루타 박민찬(5회) 김영재(4회) 박의현(4회).",
    "content": "<p>다윗 야구 선교단은 ibk야구단전에서 10안타 0홈런 4도루를 기록했습니다.</p><p>주요 기록은 3루타 강대철(3회) 박의현(2회) 은영환(2회), 2루타 박민찬(5회) 김영재(4회) 박의현(4회)입니다.</p><p><a href=\"/games/2025-11-01-vs-ibk\">경기 상세 기록 보기</a></p>",
    "link": "/games/2025-11-01-vs-ibk",
    "gameId": "2025-11-01-vs-ibk",
    "youtube": null
  },
  {
    "id": "game-2025-10-25-vs-bluehoodies",
    "slug": "game-2025-10-25-vs-bluehoodies",
    "source": "game-record",
    "autoGenerated": true,
    "category": "경기 기록",
    "title": "다윗 야구 선교단, (유신)블루후디스전 경기 기록 업데이트",
    "date": "2025-10-25",
    "summary": "다윗 야구 선교단은 9안타 0홈런 7도루를 기록했습니다. 주요 기록: 도루 반석훈(3회,4회,5회) 김재영(1회) 오치송(1회) 박의현(1회) 김성호(3회) 금교현(3회,5회) 성백동(5회) 박원주(5회) 오주영(5회) 이재신(5회), 폭투 반석훈(2개) 윤재성(2개) 오주영(1개) 박의현(1개).",
    "content": "<p>다윗 야구 선교단은 (유신)블루후디스전에서 9안타 0홈런 7도루를 기록했습니다.</p><p>주요 기록은 도루 반석훈(3회,4회,5회) 김재영(1회) 오치송(1회) 박의현(1회) 김성호(3회) 금교현(3회,5회) 성백동(5회) 박원주(5회) 오주영(5회) 이재신(5회), 폭투 반석훈(2개) 윤재성(2개) 오주영(1개) 박의현(1개)입니다.</p><p><a href=\"/games/2025-10-25-vs-bluehoodies\">경기 상세 기록 보기</a></p>",
    "link": "/games/2025-10-25-vs-bluehoodies",
    "gameId": "2025-10-25-vs-bluehoodies",
    "youtube": null
  },
  {
    "id": "game-2025-10-11-vs-swains",
    "slug": "game-2025-10-11-vs-swains",
    "source": "game-record",
    "autoGenerated": true,
    "category": "경기 기록",
    "title": "다윗 야구 선교단, 스웨인즈전 경기 기록 업데이트",
    "date": "2025-10-11",
    "summary": "다윗 야구 선교단은 11안타 0홈런 4도루를 기록했습니다. 주요 기록: 2루타 오치송(3회) 최정훈(3회) 서우성(3회) 윤성수(3회), 도루 오치송(3회) 전병진(3회) 민재홍(3회) 윤성수(1회) 오명송(1회) 이정호(1회).",
    "content": "<p>다윗 야구 선교단은 스웨인즈전에서 11안타 0홈런 4도루를 기록했습니다.</p><p>주요 기록은 2루타 오치송(3회) 최정훈(3회) 서우성(3회) 윤성수(3회), 도루 오치송(3회) 전병진(3회) 민재홍(3회) 윤성수(1회) 오명송(1회) 이정호(1회)입니다.</p><p><a href=\"/games/2025-10-11-vs-swains\">경기 상세 기록 보기</a></p>",
    "link": "/games/2025-10-11-vs-swains",
    "gameId": "2025-10-11-vs-swains",
    "youtube": null
  },
  {
    "id": "game-2025-10-11-vs-yagurepublic",
    "slug": "game-2025-10-11-vs-yagurepublic",
    "source": "game-record",
    "autoGenerated": true,
    "category": "경기 기록",
    "title": "다윗 야구 선교단, 야구공화국전 경기 기록 업데이트",
    "date": "2025-10-11",
    "summary": "다윗 야구 선교단은 9안타 1홈런 3도루를 기록했습니다. 주요 기록: 홈런 은영환(1회), 3루타 김재영(2회).",
    "content": "<p>다윗 야구 선교단은 야구공화국전에서 9안타 1홈런 3도루를 기록했습니다.</p><p>주요 기록은 홈런 은영환(1회), 3루타 김재영(2회)입니다.</p><p><a href=\"/games/2025-10-11-vs-yagurepublic\">경기 상세 기록 보기</a></p>",
    "link": "/games/2025-10-11-vs-yagurepublic",
    "gameId": "2025-10-11-vs-yagurepublic",
    "youtube": null
  },
  {
    "id": "game-2025-09-27-vs-saguholic",
    "slug": "game-2025-09-27-vs-saguholic",
    "source": "game-record",
    "autoGenerated": true,
    "category": "경기 기록",
    "title": "다윗 야구 선교단, 사구홀릭전 경기 기록 업데이트",
    "date": "2025-09-27",
    "summary": "다윗 야구 선교단은 18안타 1홈런 9도루를 기록했습니다. 주요 기록: 홈런 선예환(3회), 3루타 은영환(1회).",
    "content": "<p>다윗 야구 선교단은 사구홀릭전에서 18안타 1홈런 9도루를 기록했습니다.</p><p>주요 기록은 홈런 선예환(3회), 3루타 은영환(1회)입니다.</p><p><a href=\"/games/2025-09-27-vs-saguholic\">경기 상세 기록 보기</a></p>",
    "link": "/games/2025-09-27-vs-saguholic",
    "gameId": "2025-09-27-vs-saguholic",
    "youtube": null
  },
  {
    "id": "game-2025-09-20-vs-koreax",
    "slug": "game-2025-09-20-vs-koreax",
    "source": "game-record",
    "autoGenerated": true,
    "category": "경기 기록",
    "title": "다윗 야구 선교단, 한국거래소전 경기 기록 업데이트",
    "date": "2025-09-20",
    "summary": "다윗 야구 선교단은 12안타 4홈런 3도루를 기록했습니다. 주요 기록: 홈런 반석훈(1회,3회) 박의현(2회,3회), 3루타 윤영선(3회) 김재영(1회) 박의현(1회).",
    "content": "<p>다윗 야구 선교단은 한국거래소전에서 12안타 4홈런 3도루를 기록했습니다.</p><p>주요 기록은 홈런 반석훈(1회,3회) 박의현(2회,3회), 3루타 윤영선(3회) 김재영(1회) 박의현(1회)입니다.</p><p><a href=\"/games/2025-09-20-vs-koreax\">경기 상세 기록 보기</a></p>",
    "link": "/games/2025-09-20-vs-koreax",
    "gameId": "2025-09-20-vs-koreax",
    "youtube": null
  },
  {
    "id": "game-2025-08-30-vs-cubs2",
    "slug": "game-2025-08-30-vs-cubs2",
    "source": "game-record",
    "autoGenerated": true,
    "category": "경기 기록",
    "title": "다윗 야구 선교단, 시카고컵스2전 경기 기록 업데이트",
    "date": "2025-08-30",
    "summary": "다윗 야구 선교단은 13안타 1홈런 4도루를 기록했습니다. 주요 기록: 홈런 선예환(5회), 3루타 선예환(2회) 최정훈(5회).",
    "content": "<p>다윗 야구 선교단은 시카고컵스2전에서 13안타 1홈런 4도루를 기록했습니다.</p><p>주요 기록은 홈런 선예환(5회), 3루타 선예환(2회) 최정훈(5회)입니다.</p><p><a href=\"/games/2025-08-30-vs-cubs2\">경기 상세 기록 보기</a></p>",
    "link": "/games/2025-08-30-vs-cubs2",
    "gameId": "2025-08-30-vs-cubs2",
    "youtube": null
  },
  {
    "id": "game-2025-08-09-vs-katri",
    "slug": "game-2025-08-09-vs-katri",
    "source": "game-record",
    "autoGenerated": true,
    "category": "경기 기록",
    "title": "다윗 야구 선교단, KATRI시험연구원전 경기 기록 업데이트",
    "date": "2025-08-09",
    "summary": "다윗 야구 선교단은 17안타 1홈런 8도루를 기록했습니다. 주요 기록: 홈런 박의현(1회), 2루타 김재영(1회) 박의현(4회) 황홍철(1회) 조영중(1회).",
    "content": "<p>다윗 야구 선교단은 KATRI시험연구원전에서 17안타 1홈런 8도루를 기록했습니다.</p><p>주요 기록은 홈런 박의현(1회), 2루타 김재영(1회) 박의현(4회) 황홍철(1회) 조영중(1회)입니다.</p><p><a href=\"/games/2025-08-09-vs-katri\">경기 상세 기록 보기</a></p>",
    "link": "/games/2025-08-09-vs-katri",
    "gameId": "2025-08-09-vs-katri",
    "youtube": null
  },
  {
    "id": "game-2025-08-09-vs-zoogla",
    "slug": "game-2025-08-09-vs-zoogla",
    "source": "game-record",
    "autoGenerated": true,
    "category": "경기 기록",
    "title": "다윗 야구 선교단, ZOOGLA GO전 경기 기록 업데이트",
    "date": "2025-08-09",
    "summary": "다윗 야구 선교단은 5안타 0홈런 7도루를 기록했습니다. 주요 기록: 3루타 은영환(3회), 2루타 백정덕(1회) 김재영(1회).",
    "content": "<p>다윗 야구 선교단은 ZOOGLA GO전에서 5안타 0홈런 7도루를 기록했습니다.</p><p>주요 기록은 3루타 은영환(3회), 2루타 백정덕(1회) 김재영(1회)입니다.</p><p><a href=\"/games/2025-08-09-vs-zoogla\">경기 상세 기록 보기</a></p>",
    "link": "/games/2025-08-09-vs-zoogla",
    "gameId": "2025-08-09-vs-zoogla",
    "youtube": null
  },
  {
    "id": "game-2025-07-19-vs-polaris",
    "slug": "game-2025-07-19-vs-polaris",
    "source": "game-record",
    "autoGenerated": true,
    "category": "경기 기록",
    "title": "다윗 야구 선교단, Polaris전 경기 기록 업데이트",
    "date": "2025-07-19",
    "summary": "다윗 야구 선교단은 6안타 0홈런 9도루를 기록했습니다. 주요 기록: 3루타 김호태(1회), 2루타 김재영(2회) 조영중(1회) 은영환(2회).",
    "content": "<p>다윗 야구 선교단은 Polaris전에서 6안타 0홈런 9도루를 기록했습니다.</p><p>주요 기록은 3루타 김호태(1회), 2루타 김재영(2회) 조영중(1회) 은영환(2회)입니다.</p><p><a href=\"/games/2025-07-19-vs-polaris\">경기 상세 기록 보기</a></p>",
    "link": "/games/2025-07-19-vs-polaris",
    "gameId": "2025-07-19-vs-polaris",
    "youtube": null
  },
  {
    "id": "game-2025-06-28-vs-gymonsters",
    "slug": "game-2025-06-28-vs-gymonsters",
    "source": "game-record",
    "autoGenerated": true,
    "category": "경기 기록",
    "title": "다윗 야구 선교단, GY몬스터즈전 경기 기록 업데이트",
    "date": "2025-06-28",
    "summary": "다윗 야구 선교단은 5안타 0홈런 6도루를 기록했습니다. 주요 기록: 홈런 백경민(5회) 정종민(2회) 강유성(4회), 2루타 정종윤(1회) 정종민(5회) 김태완(3회).",
    "content": "<p>다윗 야구 선교단은 GY몬스터즈전에서 5안타 0홈런 6도루를 기록했습니다.</p><p>주요 기록은 홈런 백경민(5회) 정종민(2회) 강유성(4회), 2루타 정종윤(1회) 정종민(5회) 김태완(3회)입니다.</p><p><a href=\"/games/2025-06-28-vs-gymonsters\">경기 상세 기록 보기</a></p>",
    "link": "/games/2025-06-28-vs-gymonsters",
    "gameId": "2025-06-28-vs-gymonsters",
    "youtube": null
  },
  {
    "id": "game-2025-06-14-vs-maestro",
    "slug": "game-2025-06-14-vs-maestro",
    "source": "game-record",
    "autoGenerated": true,
    "category": "경기 기록",
    "title": "다윗 야구 선교단, 마에스트로전 경기 기록 업데이트",
    "date": "2025-06-14",
    "summary": "다윗 야구 선교단은 21안타 1홈런 4도루를 기록했습니다. 주요 기록: 홈런 선예환(1회), 2루타 박의현(2회) 김명선(3회) 성백동(1회) 최정훈(3회) 선예환(4회) 은영환(3회,4회).",
    "content": "<p>다윗 야구 선교단은 마에스트로전에서 21안타 1홈런 4도루를 기록했습니다.</p><p>주요 기록은 홈런 선예환(1회), 2루타 박의현(2회) 김명선(3회) 성백동(1회) 최정훈(3회) 선예환(4회) 은영환(3회,4회)입니다.</p><p><a href=\"/games/2025-06-14-vs-maestro\">경기 상세 기록 보기</a></p>",
    "link": "/games/2025-06-14-vs-maestro",
    "gameId": "2025-06-14-vs-maestro",
    "youtube": null
  },
  {
    "id": "game-2025-06-07-vs-blackduck",
    "slug": "game-2025-06-07-vs-blackduck",
    "source": "game-record",
    "autoGenerated": true,
    "category": "경기 기록",
    "title": "다윗 야구 선교단, 블랙덕전 경기 기록 업데이트",
    "date": "2025-06-07",
    "summary": "다윗 야구 선교단은 8안타 0홈런 4도루를 기록했습니다. 주요 기록: 2루타 김명선(2회) 강태영(3회) 박태일(4회), 도루 박의현(5회) 최정훈(2회) 김재영(3회,5회) 조수연(1회,3회) 강태영(5회) 하태웅(5회) 양호성(2회) 정진욱(2회,3회) 박태일(3회,4회) 신민철(2회,3회).",
    "content": "<p>다윗 야구 선교단은 블랙덕전에서 8안타 0홈런 4도루를 기록했습니다.</p><p>주요 기록은 2루타 김명선(2회) 강태영(3회) 박태일(4회), 도루 박의현(5회) 최정훈(2회) 김재영(3회,5회) 조수연(1회,3회) 강태영(5회) 하태웅(5회) 양호성(2회) 정진욱(2회,3회) 박태일(3회,4회) 신민철(2회,3회)입니다.</p><p><a href=\"/games/2025-06-07-vs-blackduck\">경기 상세 기록 보기</a></p>",
    "link": "/games/2025-06-07-vs-blackduck",
    "gameId": "2025-06-07-vs-blackduck",
    "youtube": null
  },
  {
    "id": "game-2025-05-31-vs-heukrang",
    "slug": "game-2025-05-31-vs-heukrang",
    "source": "game-record",
    "autoGenerated": true,
    "category": "경기 기록",
    "title": "다윗 야구 선교단, 흑랑전 경기 기록 업데이트",
    "date": "2025-05-31",
    "summary": "다윗 야구 선교단은 11안타 1홈런 11도루를 기록했습니다. 주요 기록: 홈런 박의현(3회), 3루타 김호성(5회).",
    "content": "<p>다윗 야구 선교단은 흑랑전에서 11안타 1홈런 11도루를 기록했습니다.</p><p>주요 기록은 홈런 박의현(3회), 3루타 김호성(5회)입니다.</p><p><a href=\"/games/2025-05-31-vs-heukrang\">경기 상세 기록 보기</a></p>",
    "link": "/games/2025-05-31-vs-heukrang",
    "gameId": "2025-05-31-vs-heukrang",
    "youtube": null
  },
  {
    "id": "game-2025-05-24-vs-ninetybros",
    "slug": "game-2025-05-24-vs-ninetybros",
    "source": "game-record",
    "autoGenerated": true,
    "category": "경기 기록",
    "title": "다윗 야구 선교단, 나인티브로스전 경기 기록 업데이트",
    "date": "2025-05-24",
    "summary": "다윗 야구 선교단은 9안타 1홈런 5도루를 기록했습니다. 주요 기록: 홈런 박의현(5회), 3루타 지성찬(3회).",
    "content": "<p>다윗 야구 선교단은 나인티브로스전에서 9안타 1홈런 5도루를 기록했습니다.</p><p>주요 기록은 홈런 박의현(5회), 3루타 지성찬(3회)입니다.</p><p><a href=\"/games/2025-05-24-vs-ninetybros\">경기 상세 기록 보기</a></p>",
    "link": "/games/2025-05-24-vs-ninetybros",
    "gameId": "2025-05-24-vs-ninetybros",
    "youtube": null
  },
  {
    "id": "game-2025-05-17-vs-wisebase",
    "slug": "game-2025-05-17-vs-wisebase",
    "source": "game-record",
    "autoGenerated": true,
    "category": "경기 기록",
    "title": "다윗 야구 선교단, 리얼위세바세전 경기 기록 업데이트",
    "date": "2025-05-17",
    "summary": "다윗 야구 선교단은 11안타 1홈런 4도루를 기록했습니다. 주요 기록: 홈런 김선양(3회), 3루타 박의현(2회) 최정훈(5회) 반석훈(3회) 김명선(3회) 정영기(4회).",
    "content": "<p>다윗 야구 선교단은 리얼위세바세전에서 11안타 1홈런 4도루를 기록했습니다.</p><p>주요 기록은 홈런 김선양(3회), 3루타 박의현(2회) 최정훈(5회) 반석훈(3회) 김명선(3회) 정영기(4회)입니다.</p><p><a href=\"/games/2025-05-17-vs-wisebase\">경기 상세 기록 보기</a></p>",
    "link": "/games/2025-05-17-vs-wisebase",
    "gameId": "2025-05-17-vs-wisebase",
    "youtube": null
  },
  {
    "id": "game-2025-03-22-vs-nanumi",
    "slug": "game-2025-03-22-vs-nanumi",
    "source": "game-record",
    "autoGenerated": true,
    "category": "경기 기록",
    "title": "다윗 야구 선교단, 농협캐피탈 나누미야구단전 경기 기록 업데이트",
    "date": "2025-03-22",
    "summary": "다윗 야구 선교단은 8안타 0홈런 6도루를 기록했습니다. 주요 기록: 3루타 최정훈(1회), 2루타 김선양(4회) 박영준(1회,3회).",
    "content": "<p>다윗 야구 선교단은 농협캐피탈 나누미야구단전에서 8안타 0홈런 6도루를 기록했습니다.</p><p>주요 기록은 3루타 최정훈(1회), 2루타 김선양(4회) 박영준(1회,3회)입니다.</p><p><a href=\"/games/2025-03-22-vs-nanumi\">경기 상세 기록 보기</a></p>",
    "link": "/games/2025-03-22-vs-nanumi",
    "gameId": "2025-03-22-vs-nanumi",
    "youtube": null
  },
  {
    "id": "game-2025-03-15-vs-cubs",
    "slug": "game-2025-03-15-vs-cubs",
    "source": "game-record",
    "autoGenerated": true,
    "category": "경기 기록",
    "title": "다윗 야구 선교단, Chicago Cubs전 경기 기록 업데이트",
    "date": "2025-03-15",
    "summary": "다윗 야구 선교단은 9안타 0홈런 2도루를 기록했습니다. 주요 기록: 2루타 박현석(4회) 김대희(2회) 지성찬(1회) 최정훈(2회), 도루 윤재성(3회) 서지용(3회) 권재연(1회,2회) 김선양(1회) 최정훈(2회).",
    "content": "<p>다윗 야구 선교단은 Chicago Cubs전에서 9안타 0홈런 2도루를 기록했습니다.</p><p>주요 기록은 2루타 박현석(4회) 김대희(2회) 지성찬(1회) 최정훈(2회), 도루 윤재성(3회) 서지용(3회) 권재연(1회,2회) 김선양(1회) 최정훈(2회)입니다.</p><p><a href=\"/games/2025-03-15-vs-cubs\">경기 상세 기록 보기</a></p>",
    "link": "/games/2025-03-15-vs-cubs",
    "gameId": "2025-03-15-vs-cubs",
    "youtube": null
  }
]
