[
  {
    "id": "2025-09-team",
    "title": "2025년 9월 11번가 와이번스전 단체사진",
    "date": "2025-09-28",
    "year": 2025,
    "group": "전체",
    "category": "정기 경기",
    "image": ""
  },
  {
    "id": "2026-03-team",
    "title": "2026 시즌 개막 단체사진",
    "date": "2026-03-15",
    "year": 2026,
    "group": "전체",
    "category": "행사",
    "image": ""
  },
  {
    "id": "2026-a-team",
    "title": "A조 정기 연습 단체사진",
    "date": "2026-04-12",
    "year": 2026,
    "group": "A",
    "category": "연습",
    "image": ""
  },
  {
    "id": "2026-d-team",
    "title": "D조 정기 연습 단체사진",
    "date": "2026-04-19",
    "year": 2026,
    "group": "D",
    "category": "연습",
    "image": ""
  }
]
